{
  "context": {
    "date": "2023-10-17T01:36:23+02:00",
    "host_name": "ecm-rtx",
    "executable": "./build/double44",
    "num_cpus": 20,
    "mhz_per_cpu": 2625,
    "cpu_scaling_enabled": false,
    "caches": [
      {
        "type": "Data",
        "level": 1,
        "size": 32768,
        "num_sharing": 2
      },
      {
        "type": "Instruction",
        "level": 1,
        "size": 32768,
        "num_sharing": 2
      },
      {
        "type": "Unified",
        "level": 2,
        "size": 1048576,
        "num_sharing": 2
      },
      {
        "type": "Unified",
        "level": 3,
        "size": 14417920,
        "num_sharing": 20
      }
    ],
    "load_avg": [1,1.03,1],
    "library_build_type": "release"
  },
  "benchmarks": [
    {
      "name": "BM_intt_to_intt",
      "family_index": 0,
      "per_family_instance_index": 0,
      "run_name": "BM_intt_to_intt",
      "run_type": "iteration",
      "repetitions": 10,
      "repetition_index": 0,
      "threads": 1,
      "iterations": 7,
      "real_time": 1.0071417210357530e+08,
      "cpu_time": 1.0070476471428564e+08,
      "time_unit": "ns"
    },
    {
      "name": "BM_intt_to_intt",
      "family_index": 0,
      "per_family_instance_index": 0,
      "run_name": "BM_intt_to_intt",
      "run_type": "iteration",
      "repetitions": 10,
      "repetition_index": 1,
      "threads": 1,
      "iterations": 7,
      "real_time": 1.0061257492218699e+08,
      "cpu_time": 1.0060520742857169e+08,
      "time_unit": "ns"
    },
    {
      "name": "BM_intt_to_intt",
      "family_index": 0,
      "per_family_instance_index": 0,
      "run_name": "BM_intt_to_intt",
      "run_type": "iteration",
      "repetitions": 10,
      "repetition_index": 2,
      "threads": 1,
      "iterations": 7,
      "real_time": 1.0074012540280819e+08,
      "cpu_time": 1.0073326757142885e+08,
      "time_unit": "ns"
    },
    {
      "name": "BM_intt_to_intt",
      "family_index": 0,
      "per_family_instance_index": 0,
      "run_name": "BM_intt_to_intt",
      "run_type": "iteration",
      "repetitions": 10,
      "repetition_index": 3,
      "threads": 1,
      "iterations": 7,
      "real_time": 1.0065876958625658e+08,
      "cpu_time": 1.0064855614285710e+08,
      "time_unit": "ns"
    },
    {
      "name": "BM_intt_to_intt",
      "family_index": 0,
      "per_family_instance_index": 0,
      "run_name": "BM_intt_to_intt",
      "run_type": "iteration",
      "repetitions": 10,
      "repetition_index": 4,
      "threads": 1,
      "iterations": 7,
      "real_time": 1.0060983976083143e+08,
      "cpu_time": 1.0060220685714327e+08,
      "time_unit": "ns"
    },
    {
      "name": "BM_intt_to_intt",
      "family_index": 0,
      "per_family_instance_index": 0,
      "run_name": "BM_intt_to_intt",
      "run_type": "iteration",
      "repetitions": 10,
      "repetition_index": 5,
      "threads": 1,
      "iterations": 7,
      "real_time": 1.0059732251933643e+08,
      "cpu_time": 1.0058296000000031e+08,
      "time_unit": "ns"
    },
    {
      "name": "BM_intt_to_intt",
      "family_index": 0,
      "per_family_instance_index": 0,
      "run_name": "BM_intt_to_intt",
      "run_type": "iteration",
      "repetitions": 10,
      "repetition_index": 6,
      "threads": 1,
      "iterations": 7,
      "real_time": 1.0065200259642942e+08,
      "cpu_time": 1.0063809914285775e+08,
      "time_unit": "ns"
    },
    {
      "name": "BM_intt_to_intt",
      "family_index": 0,
      "per_family_instance_index": 0,
      "run_name": "BM_intt_to_intt",
      "run_type": "iteration",
      "repetitions": 10,
      "repetition_index": 7,
      "threads": 1,
      "iterations": 7,
      "real_time": 1.0070297920278141e+08,
      "cpu_time": 1.0069207285714351e+08,
      "time_unit": "ns"
    },
    {
      "name": "BM_intt_to_intt",
      "family_index": 0,
      "per_family_instance_index": 0,
      "run_name": "BM_intt_to_intt",
      "run_type": "iteration",
      "repetitions": 10,
      "repetition_index": 8,
      "threads": 1,
      "iterations": 7,
      "real_time": 1.0065052871193205e+08,
      "cpu_time": 1.0064089328571464e+08,
      "time_unit": "ns"
    },
    {
      "name": "BM_intt_to_intt",
      "family_index": 0,
      "per_family_instance_index": 0,
      "run_name": "BM_intt_to_intt",
      "run_type": "iteration",
      "repetitions": 10,
      "repetition_index": 9,
      "threads": 1,
      "iterations": 7,
      "real_time": 1.0065375853862081e+08,
      "cpu_time": 1.0064682414285743e+08,
      "time_unit": "ns"
    },
    {
      "name": "BM_intt_to_intt_mean",
      "family_index": 0,
      "per_family_instance_index": 0,
      "run_name": "BM_intt_to_intt",
      "run_type": "aggregate",
      "repetitions": 10,
      "threads": 1,
      "aggregate_name": "mean",
      "aggregate_unit": "time",
      "iterations": 10,
      "real_time": 1.0065920733447586e+08,
      "cpu_time": 1.0064948521428603e+08,
      "time_unit": "ns"
    },
    {
      "name": "BM_intt_to_intt_median",
      "family_index": 0,
      "per_family_instance_index": 0,
      "run_name": "BM_intt_to_intt",
      "run_type": "aggregate",
      "repetitions": 10,
      "threads": 1,
      "aggregate_name": "median",
      "aggregate_unit": "time",
      "iterations": 10,
      "real_time": 1.0065288056752512e+08,
      "cpu_time": 1.0064385871428603e+08,
      "time_unit": "ns"
    },
    {
      "name": "BM_intt_to_intt_stddev",
      "family_index": 0,
      "per_family_instance_index": 0,
      "run_name": "BM_intt_to_intt",
      "run_type": "aggregate",
      "repetitions": 10,
      "threads": 1,
      "aggregate_name": "stddev",
      "aggregate_unit": "time",
      "iterations": 10,
      "real_time": 4.7238653377633062e+04,
      "cpu_time": 4.7983552308792176e+04,
      "time_unit": "ns"
    },
    {
      "name": "BM_intt_to_intt_cv",
      "family_index": 0,
      "per_family_instance_index": 0,
      "run_name": "BM_intt_to_intt",
      "run_type": "aggregate",
      "repetitions": 10,
      "threads": 1,
      "aggregate_name": "cv",
      "aggregate_unit": "percentage",
      "iterations": 10,
      "real_time": 4.6929292042471497e-04,
      "cpu_time": 4.7673917265084507e-04,
      "time_unit": "ns"
    },
    {
      "name": "BM_intt_to_ntt",
      "family_index": 1,
      "per_family_instance_index": 0,
      "run_name": "BM_intt_to_ntt",
      "run_type": "iteration",
      "repetitions": 10,
      "repetition_index": 0,
      "threads": 1,
      "iterations": 7,
      "real_time": 1.0847555526665279e+08,
      "cpu_time": 1.0846565214285724e+08,
      "time_unit": "ns"
    },
    {
      "name": "BM_intt_to_ntt",
      "family_index": 1,
      "per_family_instance_index": 0,
      "run_name": "BM_intt_to_ntt",
      "run_type": "iteration",
      "repetitions": 10,
      "repetition_index": 1,
      "threads": 1,
      "iterations": 7,
      "real_time": 1.0841424470501287e+08,
      "cpu_time": 1.0840581785714220e+08,
      "time_unit": "ns"
    },
    {
      "name": "BM_intt_to_ntt",
      "family_index": 1,
      "per_family_instance_index": 0,
      "run_name": "BM_intt_to_ntt",
      "run_type": "iteration",
      "repetitions": 10,
      "repetition_index": 2,
      "threads": 1,
      "iterations": 7,
      "real_time": 1.0830682250005858e+08,
      "cpu_time": 1.0829528857142736e+08,
      "time_unit": "ns"
    },
    {
      "name": "BM_intt_to_ntt",
      "family_index": 1,
      "per_family_instance_index": 0,
      "run_name": "BM_intt_to_ntt",
      "run_type": "iteration",
      "repetitions": 10,
      "repetition_index": 3,
      "threads": 1,
      "iterations": 7,
      "real_time": 1.0843918818448271e+08,
      "cpu_time": 1.0839750142857087e+08,
      "time_unit": "ns"
    },
    {
      "name": "BM_intt_to_ntt",
      "family_index": 1,
      "per_family_instance_index": 0,
      "run_name": "BM_intt_to_ntt",
      "run_type": "iteration",
      "repetitions": 10,
      "repetition_index": 4,
      "threads": 1,
      "iterations": 7,
      "real_time": 1.0839416166501386e+08,
      "cpu_time": 1.0838365457142831e+08,
      "time_unit": "ns"
    },
    {
      "name": "BM_intt_to_ntt",
      "family_index": 1,
      "per_family_instance_index": 0,
      "run_name": "BM_intt_to_ntt",
      "run_type": "iteration",
      "repetitions": 10,
      "repetition_index": 5,
      "threads": 1,
      "iterations": 7,
      "real_time": 1.0851484723389149e+08,
      "cpu_time": 1.0850807157142839e+08,
      "time_unit": "ns"
    },
    {
      "name": "BM_intt_to_ntt",
      "family_index": 1,
      "per_family_instance_index": 0,
      "run_name": "BM_intt_to_ntt",
      "run_type": "iteration",
      "repetitions": 10,
      "repetition_index": 6,
      "threads": 1,
      "iterations": 7,
      "real_time": 1.0836629250219890e+08,
      "cpu_time": 1.0835858828571281e+08,
      "time_unit": "ns"
    },
    {
      "name": "BM_intt_to_ntt",
      "family_index": 1,
      "per_family_instance_index": 0,
      "run_name": "BM_intt_to_ntt",
      "run_type": "iteration",
      "repetitions": 10,
      "repetition_index": 7,
      "threads": 1,
      "iterations": 7,
      "real_time": 1.0861263663641044e+08,
      "cpu_time": 1.0860463328571412e+08,
      "time_unit": "ns"
    },
    {
      "name": "BM_intt_to_ntt",
      "family_index": 1,
      "per_family_instance_index": 0,
      "run_name": "BM_intt_to_ntt",
      "run_type": "iteration",
      "repetitions": 10,
      "repetition_index": 8,
      "threads": 1,
      "iterations": 7,
      "real_time": 1.0845660764191832e+08,
      "cpu_time": 1.0844178399999903e+08,
      "time_unit": "ns"
    },
    {
      "name": "BM_intt_to_ntt",
      "family_index": 1,
      "per_family_instance_index": 0,
      "run_name": "BM_intt_to_ntt",
      "run_type": "iteration",
      "repetitions": 10,
      "repetition_index": 9,
      "threads": 1,
      "iterations": 7,
      "real_time": 1.0859983068491732e+08,
      "cpu_time": 1.0859215042857175e+08,
      "time_unit": "ns"
    },
    {
      "name": "BM_intt_to_ntt_mean",
      "family_index": 1,
      "per_family_instance_index": 0,
      "run_name": "BM_intt_to_ntt",
      "run_type": "aggregate",
      "repetitions": 10,
      "threads": 1,
      "aggregate_name": "mean",
      "aggregate_unit": "time",
      "iterations": 10,
      "real_time": 1.0845801870205574e+08,
      "cpu_time": 1.0844531421428521e+08,
      "time_unit": "ns"
    },
    {
      "name": "BM_intt_to_ntt_median",
      "family_index": 1,
      "per_family_instance_index": 0,
      "run_name": "BM_intt_to_ntt",
      "run_type": "aggregate",
      "repetitions": 10,
      "threads": 1,
      "aggregate_name": "median",
      "aggregate_unit": "time",
      "iterations": 10,
      "real_time": 1.0844789791320050e+08,
      "cpu_time": 1.0842380092857060e+08,
      "time_unit": "ns"
    },
    {
      "name": "BM_intt_to_ntt_stddev",
      "family_index": 1,
      "per_family_instance_index": 0,
      "run_name": "BM_intt_to_ntt",
      "run_type": "aggregate",
      "repetitions": 10,
      "threads": 1,
      "aggregate_name": "stddev",
      "aggregate_unit": "time",
      "iterations": 10,
      "real_time": 9.7284695570339289e+04,
      "cpu_time": 9.9434532586857036e+04,
      "time_unit": "ns"
    },
    {
      "name": "BM_intt_to_ntt_cv",
      "family_index": 1,
      "per_family_instance_index": 0,
      "run_name": "BM_intt_to_ntt",
      "run_type": "aggregate",
      "repetitions": 10,
      "threads": 1,
      "aggregate_name": "cv",
      "aggregate_unit": "percentage",
      "iterations": 10,
      "real_time": 8.9698020242827219e-04,
      "cpu_time": 9.1690944239763929e-04,
      "time_unit": "ns"
    },
    {
      "name": "BM_ntt_to_intt",
      "family_index": 2,
      "per_family_instance_index": 0,
      "run_name": "BM_ntt_to_intt",
      "run_type": "iteration",
      "repetitions": 10,
      "repetition_index": 0,
      "threads": 1,
      "iterations": 7,
      "real_time": 1.0148987200643335e+08,
      "cpu_time": 1.0148133585714245e+08,
      "time_unit": "ns"
    },
    {
      "name": "BM_ntt_to_intt",
      "family_index": 2,
      "per_family_instance_index": 0,
      "run_name": "BM_ntt_to_intt",
      "run_type": "iteration",
      "repetitions": 10,
      "repetition_index": 1,
      "threads": 1,
      "iterations": 7,
      "real_time": 1.0161722158747061e+08,
      "cpu_time": 1.0160642514285660e+08,
      "time_unit": "ns"
    },
    {
      "name": "BM_ntt_to_intt",
      "family_index": 2,
      "per_family_instance_index": 0,
      "run_name": "BM_ntt_to_intt",
      "run_type": "iteration",
      "repetitions": 10,
      "repetition_index": 2,
      "threads": 1,
      "iterations": 7,
      "real_time": 1.0171692126563618e+08,
      "cpu_time": 1.0170767314285557e+08,
      "time_unit": "ns"
    },
    {
      "name": "BM_ntt_to_intt",
      "family_index": 2,
      "per_family_instance_index": 0,
      "run_name": "BM_ntt_to_intt",
      "run_type": "iteration",
      "repetitions": 10,
      "repetition_index": 3,
      "threads": 1,
      "iterations": 7,
      "real_time": 1.0164234361478260e+08,
      "cpu_time": 1.0163492785714416e+08,
      "time_unit": "ns"
    },
    {
      "name": "BM_ntt_to_intt",
      "family_index": 2,
      "per_family_instance_index": 0,
      "run_name": "BM_ntt_to_intt",
      "run_type": "iteration",
      "repetitions": 10,
      "repetition_index": 4,
      "threads": 1,
      "iterations": 7,
      "real_time": 1.0158259421586990e+08,
      "cpu_time": 1.0157515800000080e+08,
      "time_unit": "ns"
    },
    {
      "name": "BM_ntt_to_intt",
      "family_index": 2,
      "per_family_instance_index": 0,
      "run_name": "BM_ntt_to_intt",
      "run_type": "iteration",
      "repetitions": 10,
      "repetition_index": 5,
      "threads": 1,
      "iterations": 7,
      "real_time": 1.0159895595695291e+08,
      "cpu_time": 1.0158956942857297e+08,
      "time_unit": "ns"
    },
    {
      "name": "BM_ntt_to_intt",
      "family_index": 2,
      "per_family_instance_index": 0,
      "run_name": "BM_ntt_to_intt",
      "run_type": "iteration",
      "repetitions": 10,
      "repetition_index": 6,
      "threads": 1,
      "iterations": 7,
      "real_time": 1.0143954679369926e+08,
      "cpu_time": 1.0142842171428259e+08,
      "time_unit": "ns"
    },
    {
      "name": "BM_ntt_to_intt",
      "family_index": 2,
      "per_family_instance_index": 0,
      "run_name": "BM_ntt_to_intt",
      "run_type": "iteration",
      "repetitions": 10,
      "repetition_index": 7,
      "threads": 1,
      "iterations": 7,
      "real_time": 1.0149131342768669e+08,
      "cpu_time": 1.0147990399999735e+08,
      "time_unit": "ns"
    },
    {
      "name": "BM_ntt_to_intt",
      "family_index": 2,
      "per_family_instance_index": 0,
      "run_name": "BM_ntt_to_intt",
      "run_type": "iteration",
      "repetitions": 10,
      "repetition_index": 8,
      "threads": 1,
      "iterations": 7,
      "real_time": 1.0153863818517753e+08,
      "cpu_time": 1.0152875014285760e+08,
      "time_unit": "ns"
    },
    {
      "name": "BM_ntt_to_intt",
      "family_index": 2,
      "per_family_instance_index": 0,
      "run_name": "BM_ntt_to_intt",
      "run_type": "iteration",
      "repetitions": 10,
      "repetition_index": 9,
      "threads": 1,
      "iterations": 7,
      "real_time": 1.0147532820701599e+08,
      "cpu_time": 1.0146775728570999e+08,
      "time_unit": "ns"
    },
    {
      "name": "BM_ntt_to_intt_mean",
      "family_index": 2,
      "per_family_instance_index": 0,
      "run_name": "BM_ntt_to_intt",
      "run_type": "aggregate",
      "repetitions": 10,
      "threads": 1,
      "aggregate_name": "mean",
      "aggregate_unit": "time",
      "iterations": 10,
      "real_time": 1.0155927352607250e+08,
      "cpu_time": 1.0154999225714201e+08,
      "time_unit": "ns"
    },
    {
      "name": "BM_ntt_to_intt_median",
      "family_index": 2,
      "per_family_instance_index": 0,
      "run_name": "BM_ntt_to_intt",
      "run_type": "aggregate",
      "repetitions": 10,
      "threads": 1,
      "aggregate_name": "median",
      "aggregate_unit": "time",
      "iterations": 10,
      "real_time": 1.0156061620052372e+08,
      "cpu_time": 1.0155195407142921e+08,
      "time_unit": "ns"
    },
    {
      "name": "BM_ntt_to_intt_stddev",
      "family_index": 2,
      "per_family_instance_index": 0,
      "run_name": "BM_ntt_to_intt",
      "run_type": "aggregate",
      "repetitions": 10,
      "threads": 1,
      "aggregate_name": "stddev",
      "aggregate_unit": "time",
      "iterations": 10,
      "real_time": 8.7224007508882467e+04,
      "cpu_time": 8.7610841199896211e+04,
      "time_unit": "ns"
    },
    {
      "name": "BM_ntt_to_intt_cv",
      "family_index": 2,
      "per_family_instance_index": 0,
      "run_name": "BM_ntt_to_intt",
      "run_type": "aggregate",
      "repetitions": 10,
      "threads": 1,
      "aggregate_name": "cv",
      "aggregate_unit": "percentage",
      "iterations": 10,
      "real_time": 8.5884828121077629e-04,
      "cpu_time": 8.6273606971875021e-04,
      "time_unit": "ns"
    },
    {
      "name": "BM_ntt_to_ntt",
      "family_index": 3,
      "per_family_instance_index": 0,
      "run_name": "BM_ntt_to_ntt",
      "run_type": "iteration",
      "repetitions": 10,
      "repetition_index": 0,
      "threads": 1,
      "iterations": 6,
      "real_time": 1.0843313112854958e+08,
      "cpu_time": 1.0842322533333260e+08,
      "time_unit": "ns"
    },
    {
      "name": "BM_ntt_to_ntt",
      "family_index": 3,
      "per_family_instance_index": 0,
      "run_name": "BM_ntt_to_ntt",
      "run_type": "iteration",
      "repetitions": 10,
      "repetition_index": 1,
      "threads": 1,
      "iterations": 6,
      "real_time": 1.0905911245693763e+08,
      "cpu_time": 1.0904692899999921e+08,
      "time_unit": "ns"
    },
    {
      "name": "BM_ntt_to_ntt",
      "family_index": 3,
      "per_family_instance_index": 0,
      "run_name": "BM_ntt_to_ntt",
      "run_type": "iteration",
      "repetitions": 10,
      "repetition_index": 2,
      "threads": 1,
      "iterations": 6,
      "real_time": 1.0886615763107936e+08,
      "cpu_time": 1.0886072833333315e+08,
      "time_unit": "ns"
    },
    {
      "name": "BM_ntt_to_ntt",
      "family_index": 3,
      "per_family_instance_index": 0,
      "run_name": "BM_ntt_to_ntt",
      "run_type": "iteration",
      "repetitions": 10,
      "repetition_index": 3,
      "threads": 1,
      "iterations": 6,
      "real_time": 1.0892280346403520e+08,
      "cpu_time": 1.0891305116666673e+08,
      "time_unit": "ns"
    },
    {
      "name": "BM_ntt_to_ntt",
      "family_index": 3,
      "per_family_instance_index": 0,
      "run_name": "BM_ntt_to_ntt",
      "run_type": "iteration",
      "repetitions": 10,
      "repetition_index": 4,
      "threads": 1,
      "iterations": 6,
      "real_time": 1.0875597844521205e+08,
      "cpu_time": 1.0874809333333482e+08,
      "time_unit": "ns"
    },
    {
      "name": "BM_ntt_to_ntt",
      "family_index": 3,
      "per_family_instance_index": 0,
      "run_name": "BM_ntt_to_ntt",
      "run_type": "iteration",
      "repetitions": 10,
      "repetition_index": 5,
      "threads": 1,
      "iterations": 6,
      "real_time": 1.0884638161708911e+08,
      "cpu_time": 1.0883687916666912e+08,
      "time_unit": "ns"
    },
    {
      "name": "BM_ntt_to_ntt",
      "family_index": 3,
      "per_family_instance_index": 0,
      "run_name": "BM_ntt_to_ntt",
      "run_type": "iteration",
      "repetitions": 10,
      "repetition_index": 6,
      "threads": 1,
      "iterations": 6,
      "real_time": 1.0864814743399620e+08,
      "cpu_time": 1.0864223133333439e+08,
      "time_unit": "ns"
    },
    {
      "name": "BM_ntt_to_ntt",
      "family_index": 3,
      "per_family_instance_index": 0,
      "run_name": "BM_ntt_to_ntt",
      "run_type": "iteration",
      "repetitions": 10,
      "repetition_index": 7,
      "threads": 1,
      "iterations": 6,
      "real_time": 1.0850086994469166e+08,
      "cpu_time": 1.0849309983332962e+08,
      "time_unit": "ns"
    },
    {
      "name": "BM_ntt_to_ntt",
      "family_index": 3,
      "per_family_instance_index": 0,
      "run_name": "BM_ntt_to_ntt",
      "run_type": "iteration",
      "repetitions": 10,
      "repetition_index": 8,
      "threads": 1,
      "iterations": 6,
      "real_time": 1.0868373916794856e+08,
      "cpu_time": 1.0867845066666603e+08,
      "time_unit": "ns"
    },
    {
      "name": "BM_ntt_to_ntt",
      "family_index": 3,
      "per_family_instance_index": 0,
      "run_name": "BM_ntt_to_ntt",
      "run_type": "iteration",
      "repetitions": 10,
      "repetition_index": 9,
      "threads": 1,
      "iterations": 6,
      "real_time": 1.0840333874026935e+08,
      "cpu_time": 1.0839456166666870e+08,
      "time_unit": "ns"
    },
    {
      "name": "BM_ntt_to_ntt_mean",
      "family_index": 3,
      "per_family_instance_index": 0,
      "run_name": "BM_ntt_to_ntt",
      "run_type": "aggregate",
      "repetitions": 10,
      "threads": 1,
      "aggregate_name": "mean",
      "aggregate_unit": "time",
      "iterations": 10,
      "real_time": 1.0871196600298087e+08,
      "cpu_time": 1.0870372498333344e+08,
      "time_unit": "ns"
    },
    {
      "name": "BM_ntt_to_ntt_median",
      "family_index": 3,
      "per_family_instance_index": 0,
      "run_name": "BM_ntt_to_ntt",
      "run_type": "aggregate",
      "repetitions": 10,
      "threads": 1,
      "aggregate_name": "median",
      "aggregate_unit": "time",
      "iterations": 10,
      "real_time": 1.0871985880658031e+08,
      "cpu_time": 1.0871327200000045e+08,
      "time_unit": "ns"
    },
    {
      "name": "BM_ntt_to_ntt_stddev",
      "family_index": 3,
      "per_family_instance_index": 0,
      "run_name": "BM_ntt_to_ntt",
      "run_type": "aggregate",
      "repetitions": 10,
      "threads": 1,
      "aggregate_name": "stddev",
      "aggregate_unit": "time",
      "iterations": 10,
      "real_time": 2.1887936564205581e+05,
      "cpu_time": 2.1832705103517618e+05,
      "time_unit": "ns"
    },
    {
      "name": "BM_ntt_to_ntt_cv",
      "family_index": 3,
      "per_family_instance_index": 0,
      "run_name": "BM_ntt_to_ntt",
      "run_type": "aggregate",
      "repetitions": 10,
      "threads": 1,
      "aggregate_name": "cv",
      "aggregate_unit": "percentage",
      "iterations": 10,
      "real_time": 2.0133879800872537e-03,
      "cpu_time": 2.0084597015295504e-03,
      "time_unit": "ns"
    }
  ]
}
